oauth1/__init__.py
oauth1/authenticationutils.py
oauth1/coreutils.py
oauth1/oauth.py
oauth1/oauth_ext.py
oauth1/signer.py
oauth1/signer_interceptor.py
oauth1/version.py
tests/__init__.py
tests/test_interceptor.py
tests/test_oauth.py
tests/test_oauth_ext.py
tests/test_signer.py
tests/test_utils.py
mastercard_oauth1_signer-1.9.1.dist-info/LICENSE
mastercard_oauth1_signer-1.9.1.dist-info/METADATA
mastercard_oauth1_signer-1.9.1.dist-info/WHEEL
mastercard_oauth1_signer-1.9.1.dist-info/top_level.txt
mastercard_oauth1_signer-1.9.1.dist-info/RECORD
