Metadata-Version: 2.1
Name: mastercard-oauth1-signer
Version: 1.9.1
Summary: Mastercard OAuth1 Signer.
Home-page: https://github.com/Mastercard/oauth1-signer-python
Author: Mastercard
Author-email: UNKNOWN
License: MIT
Platform: UNKNOWN
Classifier: Intended Audience :: Developers
Classifier: Natural Language :: English
Classifier: Operating System :: OS Independent
Classifier: Programming Language :: Python :: 3.6
Classifier: Programming Language :: Python :: 3.7
Classifier: Programming Language :: Python :: 3.8
Classifier: Topic :: Software Development :: Libraries :: Python Modules
Requires-Dist: requests
Requires-Dist: cryptography>=42.0.0
Requires-Dist: urllib3
Requires-Dist: Deprecated
